hypper/__init__.py
hypper/base.py
hypper/hypergraph.py
hypper/logger.conf
hypper/utils.py
hypper/classification/__init__.py
hypper/classification/classification.py
hypper/data/__init__.py
hypper/data/data_reader.py
hypper/feature_selection/__init__.py
hypper/feature_selection/feature_selection.py
hypper/plotting/__init__.py
hypper/plotting/plot.py
hypper/undersampling/__init__.py
hypper/undersampling/undersampling.py
hypper-0.0.5.dist-info/LICENSE
hypper-0.0.5.dist-info/METADATA
hypper-0.0.5.dist-info/WHEEL
hypper-0.0.5.dist-info/top_level.txt
hypper-0.0.5.dist-info/RECORD
