Metadata-Version: 2.1
Name: hypper
Version: 0.0.5
Summary: Hypergraph-based data mining tool for binary classification.
Home-page: https://github.com/hypper-team/hypper
Author: Szymon Janowski, Paweł Misiorek
Author-email: szy.janowski@gmail.com, pawel.misiorek@put.poznan.pl
Project-URL: Bug Tracker, https://github.com/hypper-team/hypper/issues
Project-URL: Documentation, https://hypper-team.github.io/hypper.html
Keywords: hypergraphs machine-learning undersampling feature-selection classification
Classifier: Programming Language :: Python :: 3.7
Classifier: Programming Language :: Python :: 3.8
Classifier: Programming Language :: Python :: 3.9
Classifier: Programming Language :: Python :: 3.10
Classifier: License :: OSI Approved :: BSD License
Classifier: Operating System :: OS Independent
License-File: LICENSE
Requires-Dist: pandas (>=1.3.5)
Requires-Dist: numpy (>=1.21.0)
Requires-Dist: scikit-learn (>=1.0.2)
Requires-Dist: bidict (>=0.22.0)
Requires-Dist: psutil (>=5.9.0)
Requires-Dist: hypernetx (>=1.2.3)
Requires-Dist: requests (>=2.23.0)
Provides-Extra: all
Requires-Dist: decorator (>=5.1.1) ; extra == 'all'
Requires-Dist: pytest ; extra == 'all'
Requires-Dist: pdoc ; extra == 'all'
Requires-Dist: black ; extra == 'all'
Requires-Dist: tqdm ; extra == 'all'
Requires-Dist: pyyaml ; extra == 'all'
Requires-Dist: imbalanced-learn ; extra == 'all'
Requires-Dist: xgboost ; extra == 'all'
Requires-Dist: catboost ; extra == 'all'
Requires-Dist: lightgbm ; extra == 'all'
Provides-Extra: benchmarking
Requires-Dist: tqdm ; extra == 'benchmarking'
Requires-Dist: pyyaml ; extra == 'benchmarking'
Requires-Dist: imbalanced-learn ; extra == 'benchmarking'
Requires-Dist: xgboost ; extra == 'benchmarking'
Requires-Dist: catboost ; extra == 'benchmarking'
Requires-Dist: lightgbm ; extra == 'benchmarking'
Provides-Extra: develop
Requires-Dist: pytest ; extra == 'develop'
Requires-Dist: black ; extra == 'develop'
Provides-Extra: documentation
Requires-Dist: decorator (>=5.1.1) ; extra == 'documentation'
Requires-Dist: pdoc ; extra == 'documentation'
